euclidean_species/__init__.py
euclidean_species/main.py
euclidean_species-1.0.1.dist-info/METADATA
euclidean_species-1.0.1.dist-info/WHEEL
euclidean_species-1.0.1.dist-info/entry_points.txt
euclidean_species-1.0.1.dist-info/top_level.txt
euclidean_species-1.0.1.dist-info/RECORD
