Metadata-Version: 2.1
Name: euclidean_species
Version: 1.0.1
Requires-Python: >=3.6
Requires-Dist: pandas
